<?xml version="1.0" encoding="UTF-8" standalone="no" ?><scene formatVersion="1.0.0"><nodes><node name="CamNode"><position x="0" y="10" z="27"/><quaternion w="1" x="0" y="0" z="0"/><scale x="1" y="1" z="1"/></node><node name="Ogre/SceneRoot"><position x="0" y="0" z="0"/><quaternion w="1" x="0" y="0" z="0"/><scale x="1" y="1" z="1"/><light name="GlobalLight" type="directional"/><entity meshFile="Plane.mesh" name="BasePlane"/><node name="KOSNode_0"><position x="0" y="0" z="0"/><quaternion w="1" x="0" y="0" z="0"/><scale x="0.1" y="0.1" z="0.1"/><entity meshFile="xAxis.mesh" name="xAxis"/><entity meshFile="yAxis.mesh" name="yAxis"/><entity meshFile="zAxis.mesh" name="zAxis"/></node><node name="Barrel"><position x="10" y="10" z="0"/><quaternion w="1" x="0" y="0" z="0"/><scale x="2" y="1" z="2"/><entity meshFile="Barrel.mesh" name="Barrel"/></node><node name="mainCamFocusNode"><position x="0.5" y="-3" z="0"/><quaternion w="1" x="0" y="0" z="0"/><scale x="1" y="1" z="1"/></node></node></nodes></scene>