<mesh>
	<submeshes>
		<submesh material="zBlue" usesharedvertices="false">
			<faces count="192">
				<face v1="0" v2="1" v3="2"/>
				<face v1="3" v2="4" v3="5"/>
				<face v1="6" v2="7" v3="8"/>
				<face v1="9" v2="10" v3="11"/>
				<face v1="12" v2="13" v3="14"/>
				<face v1="15" v2="16" v3="17"/>
				<face v1="18" v2="19" v3="20"/>
				<face v1="21" v2="22" v3="23"/>
				<face v1="24" v2="25" v3="26"/>
				<face v1="27" v2="28" v3="29"/>
				<face v1="30" v2="31" v3="32"/>
				<face v1="33" v2="34" v3="35"/>
				<face v1="36" v2="37" v3="38"/>
				<face v1="39" v2="40" v3="41"/>
				<face v1="42" v2="43" v3="44"/>
				<face v1="45" v2="46" v3="47"/>
				<face v1="48" v2="49" v3="50"/>
				<face v1="51" v2="52" v3="53"/>
				<face v1="54" v2="55" v3="56"/>
				<face v1="57" v2="58" v3="59"/>
				<face v1="60" v2="61" v3="62"/>
				<face v1="63" v2="64" v3="65"/>
				<face v1="66" v2="67" v3="68"/>
				<face v1="69" v2="70" v3="71"/>
				<face v1="72" v2="73" v3="74"/>
				<face v1="75" v2="76" v3="77"/>
				<face v1="78" v2="79" v3="80"/>
				<face v1="81" v2="82" v3="83"/>
				<face v1="84" v2="85" v3="86"/>
				<face v1="87" v2="88" v3="89"/>
				<face v1="90" v2="91" v3="92"/>
				<face v1="93" v2="94" v3="95"/>
				<face v1="96" v2="97" v3="98"/>
				<face v1="99" v2="100" v3="101"/>
				<face v1="102" v2="103" v3="104"/>
				<face v1="105" v2="106" v3="107"/>
				<face v1="108" v2="109" v3="110"/>
				<face v1="111" v2="112" v3="113"/>
				<face v1="114" v2="115" v3="116"/>
				<face v1="117" v2="118" v3="119"/>
				<face v1="120" v2="121" v3="122"/>
				<face v1="123" v2="124" v3="125"/>
				<face v1="126" v2="127" v3="128"/>
				<face v1="129" v2="130" v3="131"/>
				<face v1="132" v2="133" v3="134"/>
				<face v1="135" v2="136" v3="137"/>
				<face v1="138" v2="139" v3="140"/>
				<face v1="141" v2="142" v3="143"/>
				<face v1="144" v2="145" v3="146"/>
				<face v1="147" v2="148" v3="149"/>
				<face v1="150" v2="151" v3="152"/>
				<face v1="153" v2="154" v3="155"/>
				<face v1="156" v2="157" v3="158"/>
				<face v1="159" v2="160" v3="161"/>
				<face v1="162" v2="163" v3="164"/>
				<face v1="165" v2="166" v3="167"/>
				<face v1="168" v2="169" v3="170"/>
				<face v1="171" v2="172" v3="173"/>
				<face v1="174" v2="175" v3="176"/>
				<face v1="177" v2="178" v3="179"/>
				<face v1="180" v2="181" v3="182"/>
				<face v1="183" v2="184" v3="185"/>
				<face v1="186" v2="187" v3="188"/>
				<face v1="189" v2="190" v3="191"/>
				<face v1="192" v2="193" v3="195"/>
				<face v1="193" v2="194" v3="195"/>
				<face v1="196" v2="197" v3="199"/>
				<face v1="197" v2="198" v3="199"/>
				<face v1="200" v2="201" v3="203"/>
				<face v1="201" v2="202" v3="203"/>
				<face v1="204" v2="205" v3="207"/>
				<face v1="205" v2="206" v3="207"/>
				<face v1="208" v2="209" v3="211"/>
				<face v1="209" v2="210" v3="211"/>
				<face v1="212" v2="213" v3="215"/>
				<face v1="213" v2="214" v3="215"/>
				<face v1="216" v2="217" v3="219"/>
				<face v1="217" v2="218" v3="219"/>
				<face v1="220" v2="221" v3="223"/>
				<face v1="221" v2="222" v3="223"/>
				<face v1="224" v2="225" v3="227"/>
				<face v1="225" v2="226" v3="227"/>
				<face v1="228" v2="229" v3="230"/>
				<face v1="228" v2="230" v3="231"/>
				<face v1="232" v2="233" v3="234"/>
				<face v1="232" v2="234" v3="235"/>
				<face v1="236" v2="237" v3="238"/>
				<face v1="236" v2="238" v3="239"/>
				<face v1="240" v2="241" v3="242"/>
				<face v1="240" v2="242" v3="243"/>
				<face v1="244" v2="245" v3="246"/>
				<face v1="244" v2="246" v3="247"/>
				<face v1="248" v2="249" v3="250"/>
				<face v1="248" v2="250" v3="251"/>
				<face v1="252" v2="253" v3="254"/>
				<face v1="252" v2="254" v3="255"/>
				<face v1="256" v2="257" v3="258"/>
				<face v1="256" v2="258" v3="259"/>
				<face v1="260" v2="261" v3="262"/>
				<face v1="260" v2="262" v3="263"/>
				<face v1="264" v2="265" v3="266"/>
				<face v1="264" v2="266" v3="267"/>
				<face v1="268" v2="269" v3="270"/>
				<face v1="268" v2="270" v3="271"/>
				<face v1="272" v2="273" v3="274"/>
				<face v1="272" v2="274" v3="275"/>
				<face v1="276" v2="277" v3="278"/>
				<face v1="276" v2="278" v3="279"/>
				<face v1="280" v2="281" v3="282"/>
				<face v1="280" v2="282" v3="283"/>
				<face v1="284" v2="285" v3="286"/>
				<face v1="284" v2="286" v3="287"/>
				<face v1="288" v2="289" v3="290"/>
				<face v1="288" v2="290" v3="291"/>
				<face v1="292" v2="293" v3="294"/>
				<face v1="292" v2="294" v3="295"/>
				<face v1="296" v2="297" v3="298"/>
				<face v1="296" v2="298" v3="299"/>
				<face v1="300" v2="301" v3="302"/>
				<face v1="300" v2="302" v3="303"/>
				<face v1="304" v2="305" v3="306"/>
				<face v1="304" v2="306" v3="307"/>
				<face v1="308" v2="309" v3="310"/>
				<face v1="308" v2="310" v3="311"/>
				<face v1="312" v2="313" v3="314"/>
				<face v1="312" v2="314" v3="315"/>
				<face v1="316" v2="317" v3="318"/>
				<face v1="316" v2="318" v3="319"/>
				<face v1="320" v2="321" v3="322"/>
				<face v1="323" v2="324" v3="325"/>
				<face v1="326" v2="327" v3="328"/>
				<face v1="329" v2="330" v3="331"/>
				<face v1="332" v2="333" v3="334"/>
				<face v1="335" v2="336" v3="337"/>
				<face v1="338" v2="339" v3="340"/>
				<face v1="341" v2="342" v3="343"/>
				<face v1="344" v2="345" v3="346"/>
				<face v1="347" v2="348" v3="349"/>
				<face v1="350" v2="351" v3="352"/>
				<face v1="353" v2="354" v3="355"/>
				<face v1="356" v2="357" v3="358"/>
				<face v1="359" v2="360" v3="361"/>
				<face v1="362" v2="363" v3="364"/>
				<face v1="365" v2="366" v3="367"/>
				<face v1="368" v2="369" v3="370"/>
				<face v1="371" v2="372" v3="373"/>
				<face v1="374" v2="375" v3="376"/>
				<face v1="377" v2="378" v3="379"/>
				<face v1="380" v2="381" v3="382"/>
				<face v1="383" v2="384" v3="385"/>
				<face v1="386" v2="387" v3="388"/>
				<face v1="389" v2="390" v3="391"/>
				<face v1="392" v2="393" v3="394"/>
				<face v1="395" v2="396" v3="397"/>
				<face v1="398" v2="399" v3="400"/>
				<face v1="401" v2="402" v3="403"/>
				<face v1="404" v2="405" v3="406"/>
				<face v1="407" v2="408" v3="409"/>
				<face v1="410" v2="411" v3="412"/>
				<face v1="413" v2="414" v3="415"/>
				<face v1="416" v2="417" v3="418"/>
				<face v1="419" v2="420" v3="421"/>
				<face v1="422" v2="423" v3="424"/>
				<face v1="425" v2="426" v3="427"/>
				<face v1="428" v2="429" v3="430"/>
				<face v1="431" v2="432" v3="433"/>
				<face v1="434" v2="435" v3="436"/>
				<face v1="437" v2="438" v3="439"/>
				<face v1="440" v2="441" v3="442"/>
				<face v1="443" v2="444" v3="445"/>
				<face v1="446" v2="447" v3="448"/>
				<face v1="449" v2="450" v3="451"/>
				<face v1="452" v2="453" v3="454"/>
				<face v1="455" v2="456" v3="457"/>
				<face v1="458" v2="459" v3="460"/>
				<face v1="461" v2="462" v3="463"/>
				<face v1="464" v2="465" v3="466"/>
				<face v1="467" v2="468" v3="469"/>
				<face v1="470" v2="471" v3="472"/>
				<face v1="473" v2="474" v3="475"/>
				<face v1="476" v2="477" v3="478"/>
				<face v1="479" v2="480" v3="481"/>
				<face v1="482" v2="483" v3="484"/>
				<face v1="485" v2="486" v3="487"/>
				<face v1="488" v2="489" v3="490"/>
				<face v1="491" v2="492" v3="493"/>
				<face v1="494" v2="495" v3="496"/>
				<face v1="497" v2="498" v3="499"/>
				<face v1="500" v2="501" v3="502"/>
				<face v1="503" v2="504" v3="505"/>
				<face v1="506" v2="507" v3="508"/>
				<face v1="509" v2="510" v3="511"/>
			</faces>
			<geometry vertexcount="512">
				<vertexbuffer positions="true" normals="true">
					<vertex>
						<position x="3.147063" y="2.102800" z="37.895916"/>
						<normal x="0.743697" y="0.496917" z="0.447201"/>
					</vertex>
					<vertex>
						<position x="2.676357" y="2.676357" z="37.895916"/>
						<normal x="0.632459" y="0.632459" z="0.447204"/>
					</vertex>
					<vertex>
						<position x="-0.000001" y="-0.000001" z="45.465801"/>
						<normal x="0.000000" y="0.000000" z="1.000000"/>
					</vertex>
					<vertex>
						<position x="-0.000001" y="-0.000001" z="45.465801"/>
						<normal x="0.000000" y="0.000000" z="1.000000"/>
					</vertex>
					<vertex>
						<position x="3.496829" y="1.448434" z="37.895916"/>
						<normal x="0.826350" y="0.342278" z="0.447204"/>
					</vertex>
					<vertex>
						<position x="3.147063" y="2.102800" z="37.895916"/>
						<normal x="0.743697" y="0.496917" z="0.447201"/>
					</vertex>
					<vertex>
						<position x="-0.000001" y="-0.000001" z="45.465801"/>
						<normal x="0.000000" y="0.000000" z="1.000000"/>
					</vertex>
					<vertex>
						<position x="3.712214" y="0.738405" z="37.895916"/>
						<normal x="0.877250" y="0.174480" z="0.447201"/>
					</vertex>
					<vertex>
						<position x="3.496829" y="1.448434" z="37.895916"/>
						<normal x="0.826350" y="0.342278" z="0.447204"/>
					</vertex>
					<vertex>
						<position x="-0.000001" y="-0.000001" z="45.465801"/>
						<normal x="0.000000" y="0.000000" z="1.000000"/>
					</vertex>
					<vertex>
						<position x="3.784940" y="-0.000000" z="37.895916"/>
						<normal x="0.894433" y="0.000000" z="0.447201"/>
					</vertex>
					<vertex>
						<position x="3.712214" y="0.738405" z="37.895916"/>
						<normal x="0.877250" y="0.174480" z="0.447201"/>
					</vertex>
					<vertex>
						<position x="-0.000001" y="-0.000001" z="45.465801"/>
						<normal x="0.000000" y="0.000000" z="1.000000"/>
					</vertex>
					<vertex>
						<position x="3.712214" y="-0.738406" z="37.895916"/>
						<normal x="0.877250" y="-0.174480" z="0.447201"/>
					</vertex>
					<vertex>
						<position x="3.784940" y="-0.000000" z="37.895916"/>
						<normal x="0.894433" y="0.000000" z="0.447201"/>
					</vertex>
					<vertex>
						<position x="-0.000001" y="-0.000001" z="45.465801"/>
						<normal x="0.000000" y="0.000000" z="1.000000"/>
					</vertex>
					<vertex>
						<position x="3.496829" y="-1.448434" z="37.895916"/>
						<normal x="0.826350" y="-0.342278" z="0.447204"/>
					</vertex>
					<vertex>
						<position x="3.712214" y="-0.738406" z="37.895916"/>
						<normal x="0.877250" y="-0.174480" z="0.447201"/>
					</vertex>
					<vertex>
						<position x="-0.000001" y="-0.000001" z="45.465801"/>
						<normal x="0.000000" y="0.000000" z="1.000000"/>
					</vertex>
					<vertex>
						<position x="3.147063" y="-2.102801" z="37.895916"/>
						<normal x="0.743697" y="-0.496917" z="0.447201"/>
					</vertex>
					<vertex>
						<position x="3.496829" y="-1.448434" z="37.895916"/>
						<normal x="0.826350" y="-0.342278" z="0.447204"/>
					</vertex>
					<vertex>
						<position x="-0.000001" y="-0.000001" z="45.465801"/>
						<normal x="0.000000" y="0.000000" z="1.000000"/>
					</vertex>
					<vertex>
						<position x="2.676357" y="-2.676358" z="37.895916"/>
						<normal x="0.632459" y="-0.632459" z="0.447204"/>
					</vertex>
					<vertex>
						<position x="3.147063" y="-2.102801" z="37.895916"/>
						<normal x="0.743697" y="-0.496917" z="0.447201"/>
					</vertex>
					<vertex>
						<position x="-0.000001" y="-0.000001" z="45.465801"/>
						<normal x="0.000000" y="0.000000" z="1.000000"/>
					</vertex>
					<vertex>
						<position x="2.102800" y="-3.147064" z="37.895916"/>
						<normal x="0.496917" y="-0.743697" z="0.447201"/>
					</vertex>
					<vertex>
						<position x="2.676357" y="-2.676358" z="37.895916"/>
						<normal x="0.632459" y="-0.632459" z="0.447204"/>
					</vertex>
					<vertex>
						<position x="-0.000001" y="-0.000001" z="45.465801"/>
						<normal x="0.000000" y="0.000000" z="1.000000"/>
					</vertex>
					<vertex>
						<position x="1.448433" y="-3.496831" z="37.895916"/>
						<normal x="0.342278" y="-0.826350" z="0.447204"/>
					</vertex>
					<vertex>
						<position x="2.102800" y="-3.147064" z="37.895916"/>
						<normal x="0.496917" y="-0.743697" z="0.447201"/>
					</vertex>
					<vertex>
						<position x="-0.000001" y="-0.000001" z="45.465801"/>
						<normal x="0.000000" y="0.000000" z="1.000000"/>
					</vertex>
					<vertex>
						<position x="0.738404" y="-3.712215" z="37.895916"/>
						<normal x="0.174480" y="-0.877250" z="0.447201"/>
					</vertex>
					<vertex>
						<position x="1.448433" y="-3.496831" z="37.895916"/>
						<normal x="0.342278" y="-0.826350" z="0.447204"/>
					</vertex>
					<vertex>
						<position x="-0.000001" y="-0.000001" z="45.465801"/>
						<normal x="0.000000" y="0.000000" z="1.000000"/>
					</vertex>
					<vertex>
						<position x="-0.000002" y="-3.784942" z="37.895916"/>
						<normal x="0.000000" y="-0.894433" z="0.447201"/>
					</vertex>
					<vertex>
						<position x="0.738404" y="-3.712215" z="37.895916"/>
						<normal x="0.174480" y="-0.877250" z="0.447201"/>
					</vertex>
					<vertex>
						<position x="-0.000001" y="-0.000001" z="45.465801"/>
						<normal x="0.000000" y="0.000000" z="1.000000"/>
					</vertex>
					<vertex>
						<position x="-0.738408" y="-3.712215" z="37.895916"/>
						<normal x="-0.174480" y="-0.877250" z="0.447201"/>
					</vertex>
					<vertex>
						<position x="-0.000002" y="-3.784942" z="37.895916"/>
						<normal x="0.000000" y="-0.894433" z="0.447201"/>
					</vertex>
					<vertex>
						<position x="-0.000001" y="-0.000001" z="45.465801"/>
						<normal x="0.000000" y="0.000000" z="1.000000"/>
					</vertex>
					<vertex>
						<position x="-1.448437" y="-3.496830" z="37.895916"/>
						<normal x="-0.342278" y="-0.826350" z="0.447204"/>
					</vertex>
					<vertex>
						<position x="-0.738408" y="-3.712215" z="37.895916"/>
						<normal x="-0.174480" y="-0.877250" z="0.447201"/>
					</vertex>
					<vertex>
						<position x="-0.000001" y="-0.000001" z="45.465801"/>
						<normal x="0.000000" y="0.000000" z="1.000000"/>
					</vertex>
					<vertex>
						<position x="-2.102803" y="-3.147063" z="37.895916"/>
						<normal x="-0.496917" y="-0.743697" z="0.447201"/>
					</vertex>
					<vertex>
						<position x="-1.448437" y="-3.496830" z="37.895916"/>
						<normal x="-0.342278" y="-0.826350" z="0.447204"/>
					</vertex>
					<vertex>
						<position x="-0.000001" y="-0.000001" z="45.465801"/>
						<normal x="0.000000" y="0.000000" z="1.000000"/>
					</vertex>
					<vertex>
						<position x="-2.676360" y="-2.676357" z="37.895916"/>
						<normal x="-0.632459" y="-0.632459" z="0.447204"/>
					</vertex>
					<vertex>
						<position x="-2.102803" y="-3.147063" z="37.895916"/>
						<normal x="-0.496917" y="-0.743697" z="0.447201"/>
					</vertex>
					<vertex>
						<position x="-0.000001" y="-0.000001" z="45.465801"/>
						<normal x="0.000000" y="0.000000" z="1.000000"/>
					</vertex>
					<vertex>
						<position x="-3.147066" y="-2.102799" z="37.895916"/>
						<normal x="-0.743697" y="-0.496917" z="0.447201"/>
					</vertex>
					<vertex>
						<position x="-2.676360" y="-2.676357" z="37.895916"/>
						<normal x="-0.632459" y="-0.632459" z="0.447204"/>
					</vertex>
					<vertex>
						<position x="-0.000001" y="-0.000001" z="45.465801"/>
						<normal x="0.000000" y="0.000000" z="1.000000"/>
					</vertex>
					<vertex>
						<position x="-3.496832" y="-1.448432" z="37.895916"/>
						<normal x="-0.826350" y="-0.342278" z="0.447204"/>
					</vertex>
					<vertex>
						<position x="-3.147066" y="-2.102799" z="37.895916"/>
						<normal x="-0.743697" y="-0.496917" z="0.447201"/>
					</vertex>
					<vertex>
						<position x="-0.000001" y="-0.000001" z="45.465801"/>
						<normal x="0.000000" y="0.000000" z="1.000000"/>
					</vertex>
					<vertex>
						<position x="-3.712216" y="-0.738403" z="37.895916"/>
						<normal x="-0.877250" y="-0.174480" z="0.447201"/>
					</vertex>
					<vertex>
						<position x="-3.496832" y="-1.448432" z="37.895916"/>
						<normal x="-0.826350" y="-0.342278" z="0.447204"/>
					</vertex>
					<vertex>
						<position x="-0.000001" y="-0.000001" z="45.465801"/>
						<normal x="0.000000" y="0.000000" z="1.000000"/>
					</vertex>
					<vertex>
						<position x="-3.784942" y="0.000003" z="37.895916"/>
						<normal x="-0.894433" y="0.000000" z="0.447201"/>
					</vertex>
					<vertex>
						<position x="-3.712216" y="-0.738403" z="37.895916"/>
						<normal x="-0.877250" y="-0.174480" z="0.447201"/>
					</vertex>
					<vertex>
						<position x="-0.000001" y="-0.000001" z="45.465801"/>
						<normal x="0.000000" y="0.000000" z="1.000000"/>
					</vertex>
					<vertex>
						<position x="-3.712215" y="0.738409" z="37.895916"/>
						<normal x="-0.877250" y="0.174480" z="0.447201"/>
					</vertex>
					<vertex>
						<position x="-3.784942" y="0.000003" z="37.895916"/>
						<normal x="-0.894433" y="0.000000" z="0.447201"/>
					</vertex>
					<vertex>
						<position x="-0.000001" y="-0.000001" z="45.465801"/>
						<normal x="0.000000" y="0.000000" z="1.000000"/>
					</vertex>
					<vertex>
						<position x="-3.496829" y="1.448438" z="37.895916"/>
						<normal x="-0.826350" y="0.342278" z="0.447204"/>
					</vertex>
					<vertex>
						<position x="-3.712215" y="0.738409" z="37.895916"/>
						<normal x="-0.877250" y="0.174480" z="0.447201"/>
					</vertex>
					<vertex>
						<position x="-0.000001" y="-0.000001" z="45.465801"/>
						<normal x="0.000000" y="0.000000" z="1.000000"/>
					</vertex>
					<vertex>
						<position x="-3.147062" y="2.102804" z="37.895916"/>
						<normal x="-0.743697" y="0.496917" z="0.447201"/>
					</vertex>
					<vertex>
						<position x="-3.496829" y="1.448438" z="37.895916"/>
						<normal x="-0.826350" y="0.342278" z="0.447204"/>
					</vertex>
					<vertex>
						<position x="-0.000001" y="-0.000001" z="45.465801"/>
						<normal x="0.000000" y="0.000000" z="1.000000"/>
					</vertex>
					<vertex>
						<position x="-2.676355" y="2.676360" z="37.895916"/>
						<normal x="-0.632459" y="0.632459" z="0.447204"/>
					</vertex>
					<vertex>
						<position x="-3.147062" y="2.102804" z="37.895916"/>
						<normal x="-0.743697" y="0.496917" z="0.447201"/>
					</vertex>
					<vertex>
						<position x="-0.000001" y="-0.000001" z="45.465801"/>
						<normal x="0.000000" y="0.000000" z="1.000000"/>
					</vertex>
					<vertex>
						<position x="-2.102797" y="3.147066" z="37.895916"/>
						<normal x="-0.496917" y="0.743697" z="0.447201"/>
					</vertex>
					<vertex>
						<position x="-2.676355" y="2.676360" z="37.895916"/>
						<normal x="-0.632459" y="0.632459" z="0.447204"/>
					</vertex>
					<vertex>
						<position x="-0.000001" y="-0.000001" z="45.465801"/>
						<normal x="0.000000" y="0.000000" z="1.000000"/>
					</vertex>
					<vertex>
						<position x="-1.448430" y="3.496831" z="37.895916"/>
						<normal x="-0.342278" y="0.826350" z="0.447204"/>
					</vertex>
					<vertex>
						<position x="-2.102797" y="3.147066" z="37.895916"/>
						<normal x="-0.496917" y="0.743697" z="0.447201"/>
					</vertex>
					<vertex>
						<position x="-0.000001" y="-0.000001" z="45.465801"/>
						<normal x="0.000000" y="0.000000" z="1.000000"/>
					</vertex>
					<vertex>
						<position x="-0.738401" y="3.712215" z="37.895916"/>
						<normal x="-0.174480" y="0.877250" z="0.447201"/>
					</vertex>
					<vertex>
						<position x="-1.448430" y="3.496831" z="37.895916"/>
						<normal x="-0.342278" y="0.826350" z="0.447204"/>
					</vertex>
					<vertex>
						<position x="-0.000001" y="-0.000001" z="45.465801"/>
						<normal x="0.000000" y="0.000000" z="1.000000"/>
					</vertex>
					<vertex>
						<position x="0.000005" y="3.784940" z="37.895916"/>
						<normal x="0.000000" y="0.894433" z="0.447201"/>
					</vertex>
					<vertex>
						<position x="-0.738401" y="3.712215" z="37.895916"/>
						<normal x="-0.174480" y="0.877250" z="0.447201"/>
					</vertex>
					<vertex>
						<position x="-0.000001" y="-0.000001" z="45.465801"/>
						<normal x="0.000000" y="0.000000" z="1.000000"/>
					</vertex>
					<vertex>
						<position x="0.738411" y="3.712213" z="37.895916"/>
						<normal x="0.174480" y="0.877250" z="0.447201"/>
					</vertex>
					<vertex>
						<position x="0.000005" y="3.784940" z="37.895916"/>
						<normal x="0.000000" y="0.894433" z="0.447201"/>
					</vertex>
					<vertex>
						<position x="-0.000001" y="-0.000001" z="45.465801"/>
						<normal x="0.000000" y="0.000000" z="1.000000"/>
					</vertex>
					<vertex>
						<position x="1.448440" y="3.496826" z="37.895916"/>
						<normal x="0.342278" y="0.826350" z="0.447204"/>
					</vertex>
					<vertex>
						<position x="0.738411" y="3.712213" z="37.895916"/>
						<normal x="0.174480" y="0.877250" z="0.447201"/>
					</vertex>
					<vertex>
						<position x="-0.000001" y="-0.000001" z="45.465801"/>
						<normal x="0.000000" y="0.000000" z="1.000000"/>
					</vertex>
					<vertex>
						<position x="2.102806" y="3.147059" z="37.895916"/>
						<normal x="0.496917" y="0.743697" z="0.447201"/>
					</vertex>
					<vertex>
						<position x="1.448440" y="3.496826" z="37.895916"/>
						<normal x="0.342278" y="0.826350" z="0.447204"/>
					</vertex>
					<vertex>
						<position x="-0.000001" y="-0.000001" z="45.465801"/>
						<normal x="0.000000" y="0.000000" z="1.000000"/>
					</vertex>
					<vertex>
						<position x="2.676357" y="2.676357" z="37.895916"/>
						<normal x="0.632459" y="0.632459" z="0.447204"/>
					</vertex>
					<vertex>
						<position x="2.102806" y="3.147059" z="37.895916"/>
						<normal x="0.496917" y="0.743697" z="0.447201"/>
					</vertex>
					<vertex>
						<position x="2.102806" y="3.147059" z="37.895916"/>
						<normal x="0.000000" y="0.000000" z="-1.000000"/>
					</vertex>
					<vertex>
						<position x="2.676357" y="2.676357" z="37.895916"/>
						<normal x="0.000000" y="0.000000" z="-1.000000"/>
					</vertex>
					<vertex>
						<position x="-0.000001" y="-0.000001" z="37.895916"/>
						<normal x="0.000000" y="0.000000" z="-1.000000"/>
					</vertex>
					<vertex>
						<position x="-0.000001" y="-0.000001" z="37.895916"/>
						<normal x="0.000000" y="0.000000" z="-1.000000"/>
					</vertex>
					<vertex>
						<position x="1.448440" y="3.496826" z="37.895916"/>
						<normal x="0.000000" y="0.000000" z="-1.000000"/>
					</vertex>
					<vertex>
						<position x="2.102806" y="3.147059" z="37.895916"/>
						<normal x="0.000000" y="0.000000" z="-1.000000"/>
					</vertex>
					<vertex>
						<position x="-0.000001" y="-0.000001" z="37.895916"/>
						<normal x="0.000000" y="0.000000" z="-1.000000"/>
					</vertex>
					<vertex>
						<position x="0.738411" y="3.712213" z="37.895916"/>
						<normal x="0.000000" y="0.000000" z="-1.000000"/>
					</vertex>
					<vertex>
						<position x="1.448440" y="3.496826" z="37.895916"/>
						<normal x="0.000000" y="0.000000" z="-1.000000"/>
					</vertex>
					<vertex>
						<position x="-0.000001" y="-0.000001" z="37.895916"/>
						<normal x="0.000000" y="0.000000" z="-1.000000"/>
					</vertex>
					<vertex>
						<position x="0.000005" y="3.784940" z="37.895916"/>
						<normal x="0.000000" y="0.000000" z="-1.000000"/>
					</vertex>
					<vertex>
						<position x="0.738411" y="3.712213" z="37.895916"/>
						<normal x="0.000000" y="0.000000" z="-1.000000"/>
					</vertex>
					<vertex>
						<position x="-0.000001" y="-0.000001" z="37.895916"/>
						<normal x="0.000000" y="0.000000" z="-1.000000"/>
					</vertex>
					<vertex>
						<position x="-0.738401" y="3.712215" z="37.895916"/>
						<normal x="0.000000" y="0.000000" z="-1.000000"/>
					</vertex>
					<vertex>
						<position x="0.000005" y="3.784940" z="37.895916"/>
						<normal x="0.000000" y="0.000000" z="-1.000000"/>
					</vertex>
					<vertex>
						<position x="-0.000001" y="-0.000001" z="37.895916"/>
						<normal x="0.000000" y="0.000000" z="-1.000000"/>
					</vertex>
					<vertex>
						<position x="-1.448430" y="3.496831" z="37.895916"/>
						<normal x="0.000000" y="0.000000" z="-1.000000"/>
					</vertex>
					<vertex>
						<position x="-0.738401" y="3.712215" z="37.895916"/>
						<normal x="0.000000" y="0.000000" z="-1.000000"/>
					</vertex>
					<vertex>
						<position x="-0.000001" y="-0.000001" z="37.895916"/>
						<normal x="0.000000" y="0.000000" z="-1.000000"/>
					</vertex>
					<vertex>
						<position x="-2.102797" y="3.147066" z="37.895916"/>
						<normal x="0.000000" y="0.000000" z="-1.000000"/>
					</vertex>
					<vertex>
						<position x="-1.448430" y="3.496831" z="37.895916"/>
						<normal x="0.000000" y="0.000000" z="-1.000000"/>
					</vertex>
					<vertex>
						<position x="-0.000001" y="-0.000001" z="37.895916"/>
						<normal x="0.000000" y="0.000000" z="-1.000000"/>
					</vertex>
					<vertex>
						<position x="-2.676355" y="2.676360" z="37.895916"/>
						<normal x="0.000000" y="0.000000" z="-1.000000"/>
					</vertex>
					<vertex>
						<position x="-2.102797" y="3.147066" z="37.895916"/>
						<normal x="0.000000" y="0.000000" z="-1.000000"/>
					</vertex>
					<vertex>
						<position x="-0.000001" y="-0.000001" z="37.895916"/>
						<normal x="0.000000" y="0.000000" z="-1.000000"/>
					</vertex>
					<vertex>
						<position x="-3.147062" y="2.102804" z="37.895916"/>
						<normal x="0.000000" y="0.000000" z="-1.000000"/>
					</vertex>
					<vertex>
						<position x="-2.676355" y="2.676360" z="37.895916"/>
						<normal x="0.000000" y="0.000000" z="-1.000000"/>
					</vertex>
					<vertex>
						<position x="-0.000001" y="-0.000001" z="37.895916"/>
						<normal x="0.000000" y="0.000000" z="-1.000000"/>
					</vertex>
					<vertex>
						<position x="-3.496829" y="1.448438" z="37.895916"/>
						<normal x="0.000000" y="0.000000" z="-1.000000"/>
					</vertex>
					<vertex>
						<position x="-3.147062" y="2.102804" z="37.895916"/>
						<normal x="0.000000" y="0.000000" z="-1.000000"/>
					</vertex>
					<vertex>
						<position x="-0.000001" y="-0.000001" z="37.895916"/>
						<normal x="0.000000" y="0.000000" z="-1.000000"/>
					</vertex>
					<vertex>
						<position x="-3.712215" y="0.738409" z="37.895916"/>
						<normal x="0.000000" y="0.000000" z="-1.000000"/>
					</vertex>
					<vertex>
						<position x="-3.496829" y="1.448438" z="37.895916"/>
						<normal x="0.000000" y="0.000000" z="-1.000000"/>
					</vertex>
					<vertex>
						<position x="-0.000001" y="-0.000001" z="37.895916"/>
						<normal x="0.000000" y="0.000000" z="-1.000000"/>
					</vertex>
					<vertex>
						<position x="-3.784942" y="0.000003" z="37.895916"/>
						<normal x="0.000000" y="0.000000" z="-1.000000"/>
					</vertex>
					<vertex>
						<position x="-3.712215" y="0.738409" z="37.895916"/>
						<normal x="0.000000" y="0.000000" z="-1.000000"/>
					</vertex>
					<vertex>
						<position x="-0.000001" y="-0.000001" z="37.895916"/>
						<normal x="0.000000" y="0.000000" z="-1.000000"/>
					</vertex>
					<vertex>
						<position x="-3.712216" y="-0.738403" z="37.895916"/>
						<normal x="0.000000" y="0.000000" z="-1.000000"/>
					</vertex>
					<vertex>
						<position x="-3.784942" y="0.000003" z="37.895916"/>
						<normal x="0.000000" y="0.000000" z="-1.000000"/>
					</vertex>
					<vertex>
						<position x="-0.000001" y="-0.000001" z="37.895916"/>
						<normal x="0.000000" y="0.000000" z="-1.000000"/>
					</vertex>
					<vertex>
						<position x="-3.496832" y="-1.448432" z="37.895916"/>
						<normal x="0.000000" y="0.000000" z="-1.000000"/>
					</vertex>
					<vertex>
						<position x="-3.712216" y="-0.738403" z="37.895916"/>
						<normal x="0.000000" y="0.000000" z="-1.000000"/>
					</vertex>
					<vertex>
						<position x="-0.000001" y="-0.000001" z="37.895916"/>
						<normal x="0.000000" y="0.000000" z="-1.000000"/>
					</vertex>
					<vertex>
						<position x="-3.147066" y="-2.102799" z="37.895916"/>
						<normal x="0.000000" y="0.000000" z="-1.000000"/>
					</vertex>
					<vertex>
						<position x="-3.496832" y="-1.448432" z="37.895916"/>
						<normal x="0.000000" y="0.000000" z="-1.000000"/>
					</vertex>
					<vertex>
						<position x="-0.000001" y="-0.000001" z="37.895916"/>
						<normal x="0.000000" y="0.000000" z="-1.000000"/>
					</vertex>
					<vertex>
						<position x="-2.676360" y="-2.676357" z="37.895916"/>
						<normal x="0.000000" y="0.000000" z="-1.000000"/>
					</vertex>
					<vertex>
						<position x="-3.147066" y="-2.102799" z="37.895916"/>
						<normal x="0.000000" y="0.000000" z="-1.000000"/>
					</vertex>
					<vertex>
						<position x="-0.000001" y="-0.000001" z="37.895916"/>
						<normal x="0.000000" y="0.000000" z="-1.000000"/>
					</vertex>
					<vertex>
						<position x="-2.102803" y="-3.147063" z="37.895916"/>
						<normal x="0.000000" y="0.000000" z="-1.000000"/>
					</vertex>
					<vertex>
						<position x="-2.676360" y="-2.676357" z="37.895916"/>
						<normal x="0.000000" y="0.000000" z="-1.000000"/>
					</vertex>
					<vertex>
						<position x="-0.000001" y="-0.000001" z="37.895916"/>
						<normal x="0.000000" y="0.000000" z="-1.000000"/>
					</vertex>
					<vertex>
						<position x="-1.448437" y="-3.496830" z="37.895916"/>
						<normal x="0.000000" y="0.000000" z="-1.000000"/>
					</vertex>
					<vertex>
						<position x="-2.102803" y="-3.147063" z="37.895916"/>
						<normal x="0.000000" y="0.000000" z="-1.000000"/>
					</vertex>
					<vertex>
						<position x="-0.000001" y="-0.000001" z="37.895916"/>
						<normal x="0.000000" y="0.000000" z="-1.000000"/>
					</vertex>
					<vertex>
						<position x="-0.738408" y="-3.712215" z="37.895916"/>
						<normal x="0.000000" y="0.000000" z="-1.000000"/>
					</vertex>
					<vertex>
						<position x="-1.448437" y="-3.496830" z="37.895916"/>
						<normal x="0.000000" y="0.000000" z="-1.000000"/>
					</vertex>
					<vertex>
						<position x="-0.000001" y="-0.000001" z="37.895916"/>
						<normal x="0.000000" y="0.000000" z="-1.000000"/>
					</vertex>
					<vertex>
						<position x="-0.000002" y="-3.784942" z="37.895916"/>
						<normal x="0.000000" y="0.000000" z="-1.000000"/>
					</vertex>
					<vertex>
						<position x="-0.738408" y="-3.712215" z="37.895916"/>
						<normal x="0.000000" y="0.000000" z="-1.000000"/>
					</vertex>
					<vertex>
						<position x="-0.000001" y="-0.000001" z="37.895916"/>
						<normal x="0.000000" y="0.000000" z="-1.000000"/>
					</vertex>
					<vertex>
						<position x="0.738404" y="-3.712215" z="37.895916"/>
						<normal x="0.000000" y="0.000000" z="-1.000000"/>
					</vertex>
					<vertex>
						<position x="-0.000002" y="-3.784942" z="37.895916"/>
						<normal x="0.000000" y="0.000000" z="-1.000000"/>
					</vertex>
					<vertex>
						<position x="-0.000001" y="-0.000001" z="37.895916"/>
						<normal x="0.000000" y="0.000000" z="-1.000000"/>
					</vertex>
					<vertex>
						<position x="1.448433" y="-3.496831" z="37.895916"/>
						<normal x="0.000000" y="0.000000" z="-1.000000"/>
					</vertex>
					<vertex>
						<position x="0.738404" y="-3.712215" z="37.895916"/>
						<normal x="0.000000" y="0.000000" z="-1.000000"/>
					</vertex>
					<vertex>
						<position x="-0.000001" y="-0.000001" z="37.895916"/>
						<normal x="0.000000" y="0.000000" z="-1.000000"/>
					</vertex>
					<vertex>
						<position x="2.102800" y="-3.147064" z="37.895916"/>
						<normal x="0.000000" y="0.000000" z="-1.000000"/>
					</vertex>
					<vertex>
						<position x="1.448433" y="-3.496831" z="37.895916"/>
						<normal x="0.000000" y="0.000000" z="-1.000000"/>
					</vertex>
					<vertex>
						<position x="-0.000001" y="-0.000001" z="37.895916"/>
						<normal x="0.000000" y="0.000000" z="-1.000000"/>
					</vertex>
					<vertex>
						<position x="2.676357" y="-2.676358" z="37.895916"/>
						<normal x="0.000000" y="0.000000" z="-1.000000"/>
					</vertex>
					<vertex>
						<position x="2.102800" y="-3.147064" z="37.895916"/>
						<normal x="0.000000" y="0.000000" z="-1.000000"/>
					</vertex>
					<vertex>
						<position x="-0.000001" y="-0.000001" z="37.895916"/>
						<normal x="0.000000" y="0.000000" z="-1.000000"/>
					</vertex>
					<vertex>
						<position x="3.147063" y="-2.102801" z="37.895916"/>
						<normal x="0.000000" y="0.000000" z="-1.000000"/>
					</vertex>
					<vertex>
						<position x="2.676357" y="-2.676358" z="37.895916"/>
						<normal x="0.000000" y="0.000000" z="-1.000000"/>
					</vertex>
					<vertex>
						<position x="-0.000001" y="-0.000001" z="37.895916"/>
						<normal x="0.000000" y="0.000000" z="-1.000000"/>
					</vertex>
					<vertex>
						<position x="3.496829" y="-1.448434" z="37.895916"/>
						<normal x="0.000000" y="0.000000" z="-1.000000"/>
					</vertex>
					<vertex>
						<position x="3.147063" y="-2.102801" z="37.895916"/>
						<normal x="0.000000" y="0.000000" z="-1.000000"/>
					</vertex>
					<vertex>
						<position x="-0.000001" y="-0.000001" z="37.895916"/>
						<normal x="0.000000" y="0.000000" z="-1.000000"/>
					</vertex>
					<vertex>
						<position x="3.712214" y="-0.738406" z="37.895916"/>
						<normal x="0.000000" y="0.000000" z="-1.000000"/>
					</vertex>
					<vertex>
						<position x="3.496829" y="-1.448434" z="37.895916"/>
						<normal x="0.000000" y="0.000000" z="-1.000000"/>
					</vertex>
					<vertex>
						<position x="-0.000001" y="-0.000001" z="37.895916"/>
						<normal x="0.000000" y="0.000000" z="-1.000000"/>
					</vertex>
					<vertex>
						<position x="3.784940" y="-0.000000" z="37.895916"/>
						<normal x="0.000000" y="0.000000" z="-1.000000"/>
					</vertex>
					<vertex>
						<position x="3.712214" y="-0.738406" z="37.895916"/>
						<normal x="0.000000" y="0.000000" z="-1.000000"/>
					</vertex>
					<vertex>
						<position x="-0.000001" y="-0.000001" z="37.895916"/>
						<normal x="0.000000" y="0.000000" z="-1.000000"/>
					</vertex>
					<vertex>
						<position x="3.712214" y="0.738405" z="37.895916"/>
						<normal x="0.000000" y="0.000000" z="-1.000000"/>
					</vertex>
					<vertex>
						<position x="3.784940" y="-0.000000" z="37.895916"/>
						<normal x="0.000000" y="0.000000" z="-1.000000"/>
					</vertex>
					<vertex>
						<position x="-0.000001" y="-0.000001" z="37.895916"/>
						<normal x="0.000000" y="0.000000" z="-1.000000"/>
					</vertex>
					<vertex>
						<position x="3.496829" y="1.448434" z="37.895916"/>
						<normal x="0.000000" y="0.000000" z="-1.000000"/>
					</vertex>
					<vertex>
						<position x="3.712214" y="0.738405" z="37.895916"/>
						<normal x="0.000000" y="0.000000" z="-1.000000"/>
					</vertex>
					<vertex>
						<position x="-0.000001" y="-0.000001" z="37.895916"/>
						<normal x="0.000000" y="0.000000" z="-1.000000"/>
					</vertex>
					<vertex>
						<position x="3.147063" y="2.102800" z="37.895916"/>
						<normal x="0.000000" y="0.000000" z="-1.000000"/>
					</vertex>
					<vertex>
						<position x="3.496829" y="1.448434" z="37.895916"/>
						<normal x="0.000000" y="0.000000" z="-1.000000"/>
					</vertex>
					<vertex>
						<position x="-0.000001" y="-0.000001" z="37.895916"/>
						<normal x="0.000000" y="0.000000" z="-1.000000"/>
					</vertex>
					<vertex>
						<position x="2.676357" y="2.676357" z="37.895916"/>
						<normal x="0.000000" y="0.000000" z="-1.000000"/>
					</vertex>
					<vertex>
						<position x="3.147063" y="2.102800" z="37.895916"/>
						<normal x="0.000000" y="0.000000" z="-1.000000"/>
					</vertex>
					<vertex>
						<position x="1.081898" y="1.081898" z="0.016778"/>
						<normal x="0.707107" y="0.707107" z="0.000000"/>
					</vertex>
					<vertex>
						<position x="1.081900" y="1.081896" z="38.000740"/>
						<normal x="0.707107" y="0.707107" z="0.000000"/>
					</vertex>
					<vertex>
						<position x="1.272179" y="0.850039" z="38.000740"/>
						<normal x="0.831468" y="0.555573" z="0.000000"/>
					</vertex>
					<vertex>
						<position x="1.272178" y="0.850042" z="0.016778"/>
						<normal x="0.831468" y="0.555573" z="0.000000"/>
					</vertex>
					<vertex>
						<position x="1.272178" y="0.850042" z="0.016778"/>
						<normal x="0.831468" y="0.555573" z="0.000000"/>
					</vertex>
					<vertex>
						<position x="1.272179" y="0.850039" z="38.000740"/>
						<normal x="0.831468" y="0.555573" z="0.000000"/>
					</vertex>
					<vertex>
						<position x="1.413569" y="0.585516" z="38.000740"/>
						<normal x="0.923880" y="0.382682" z="0.000000"/>
					</vertex>
					<vertex>
						<position x="1.413568" y="0.585519" z="0.016778"/>
						<normal x="0.923880" y="0.382682" z="0.000000"/>
					</vertex>
					<vertex>
						<position x="1.413568" y="0.585519" z="0.016778"/>
						<normal x="0.923880" y="0.382682" z="0.000000"/>
					</vertex>
					<vertex>
						<position x="1.413569" y="0.585516" z="38.000740"/>
						<normal x="0.923880" y="0.382682" z="0.000000"/>
					</vertex>
					<vertex>
						<position x="1.500637" y="0.298492" z="38.000740"/>
						<normal x="0.980788" y="0.195077" z="0.000000"/>
					</vertex>
					<vertex>
						<position x="1.500636" y="0.298495" z="0.016778"/>
						<normal x="0.980788" y="0.195077" z="0.000000"/>
					</vertex>
					<vertex>
						<position x="1.500636" y="0.298495" z="0.016778"/>
						<normal x="0.980788" y="0.195077" z="0.000000"/>
					</vertex>
					<vertex>
						<position x="1.500637" y="0.298492" z="38.000740"/>
						<normal x="0.980788" y="0.195077" z="0.000000"/>
					</vertex>
					<vertex>
						<position x="1.530035" y="-0.000003" z="38.000740"/>
						<normal x="1.000000" y="0.000000" z="0.000000"/>
					</vertex>
					<vertex>
						<position x="1.530035" y="0.000000" z="0.016778"/>
						<normal x="1.000000" y="0.000000" z="0.000000"/>
					</vertex>
					<vertex>
						<position x="1.530035" y="0.000000" z="0.016778"/>
						<normal x="1.000000" y="0.000000" z="0.000000"/>
					</vertex>
					<vertex>
						<position x="1.530035" y="-0.000003" z="38.000740"/>
						<normal x="1.000000" y="0.000000" z="0.000000"/>
					</vertex>
					<vertex>
						<position x="1.500635" y="-0.298497" z="38.000740"/>
						<normal x="0.980788" y="-0.195077" z="0.000000"/>
					</vertex>
					<vertex>
						<position x="1.500636" y="-0.298494" z="0.016778"/>
						<normal x="0.980788" y="-0.195077" z="0.000000"/>
					</vertex>
					<vertex>
						<position x="1.500636" y="-0.298494" z="0.016778"/>
						<normal x="0.980788" y="-0.195077" z="0.000000"/>
					</vertex>
					<vertex>
						<position x="1.500635" y="-0.298497" z="38.000740"/>
						<normal x="0.980788" y="-0.195077" z="0.000000"/>
					</vertex>
					<vertex>
						<position x="1.413567" y="-0.585521" z="38.000740"/>
						<normal x="0.923880" y="-0.382682" z="0.000000"/>
					</vertex>
					<vertex>
						<position x="1.413568" y="-0.585518" z="0.016778"/>
						<normal x="0.923880" y="-0.382682" z="0.000000"/>
					</vertex>
					<vertex>
						<position x="1.413568" y="-0.585518" z="0.016778"/>
						<normal x="0.923880" y="-0.382682" z="0.000000"/>
					</vertex>
					<vertex>
						<position x="1.413567" y="-0.585521" z="38.000740"/>
						<normal x="0.923880" y="-0.382682" z="0.000000"/>
					</vertex>
					<vertex>
						<position x="1.272177" y="-0.850043" z="38.000740"/>
						<normal x="0.831468" y="-0.555573" z="0.000000"/>
					</vertex>
					<vertex>
						<position x="1.272178" y="-0.850041" z="0.016778"/>
						<normal x="0.831468" y="-0.555573" z="0.000000"/>
					</vertex>
					<vertex>
						<position x="1.272178" y="-0.850041" z="0.016778"/>
						<normal x="0.831468" y="-0.555573" z="0.000000"/>
					</vertex>
					<vertex>
						<position x="1.272177" y="-0.850043" z="38.000740"/>
						<normal x="0.831468" y="-0.555573" z="0.000000"/>
					</vertex>
					<vertex>
						<position x="1.081897" y="-1.081898" z="38.000740"/>
						<normal x="0.707107" y="-0.707107" z="0.000000"/>
					</vertex>
					<vertex>
						<position x="1.081898" y="-1.081898" z="0.016778"/>
						<normal x="0.707107" y="-0.707107" z="0.000000"/>
					</vertex>
					<vertex>
						<position x="1.081898" y="-1.081898" z="0.016778"/>
						<normal x="0.707107" y="-0.707107" z="0.000000"/>
					</vertex>
					<vertex>
						<position x="1.081897" y="-1.081898" z="38.000740"/>
						<normal x="0.707107" y="-0.707107" z="0.000000"/>
					</vertex>
					<vertex>
						<position x="0.850042" y="-1.272177" z="38.000740"/>
						<normal x="0.555573" y="-0.831468" z="0.000000"/>
					</vertex>
					<vertex>
						<position x="0.850042" y="-1.272177" z="0.016778"/>
						<normal x="0.555573" y="-0.831468" z="0.000000"/>
					</vertex>
					<vertex>
						<position x="0.850042" y="-1.272177" z="0.016778"/>
						<normal x="0.555573" y="-0.831468" z="0.000000"/>
					</vertex>
					<vertex>
						<position x="0.850042" y="-1.272177" z="38.000740"/>
						<normal x="0.555573" y="-0.831468" z="0.000000"/>
					</vertex>
					<vertex>
						<position x="0.585519" y="-1.413568" z="38.000740"/>
						<normal x="0.382682" y="-0.923880" z="0.000000"/>
					</vertex>
					<vertex>
						<position x="0.585519" y="-1.413568" z="0.016778"/>
						<normal x="0.382682" y="-0.923880" z="0.000000"/>
					</vertex>
					<vertex>
						<position x="0.585519" y="-1.413568" z="0.016778"/>
						<normal x="0.382682" y="-0.923880" z="0.000000"/>
					</vertex>
					<vertex>
						<position x="0.585519" y="-1.413568" z="38.000740"/>
						<normal x="0.382682" y="-0.923880" z="0.000000"/>
					</vertex>
					<vertex>
						<position x="0.298496" y="-1.500635" z="38.000740"/>
						<normal x="0.195077" y="-0.980788" z="0.000000"/>
					</vertex>
					<vertex>
						<position x="0.298495" y="-1.500635" z="0.016778"/>
						<normal x="0.195077" y="-0.980788" z="0.000000"/>
					</vertex>
					<vertex>
						<position x="0.298495" y="-1.500635" z="0.016778"/>
						<normal x="0.195077" y="-0.980788" z="0.000000"/>
					</vertex>
					<vertex>
						<position x="0.298496" y="-1.500635" z="38.000740"/>
						<normal x="0.195077" y="-0.980788" z="0.000000"/>
					</vertex>
					<vertex>
						<position x="0.000002" y="-1.530034" z="38.000740"/>
						<normal x="0.000000" y="-1.000000" z="0.000000"/>
					</vertex>
					<vertex>
						<position x="-0.000000" y="-1.530034" z="0.016778"/>
						<normal x="0.000000" y="-1.000000" z="0.000000"/>
					</vertex>
					<vertex>
						<position x="-0.000000" y="-1.530034" z="0.016778"/>
						<normal x="0.000000" y="-1.000000" z="0.000000"/>
					</vertex>
					<vertex>
						<position x="0.000002" y="-1.530034" z="38.000740"/>
						<normal x="0.000000" y="-1.000000" z="0.000000"/>
					</vertex>
					<vertex>
						<position x="-0.298493" y="-1.500636" z="38.000740"/>
						<normal x="-0.195077" y="-0.980788" z="0.000000"/>
					</vertex>
					<vertex>
						<position x="-0.298495" y="-1.500635" z="0.016778"/>
						<normal x="-0.195077" y="-0.980788" z="0.000000"/>
					</vertex>
					<vertex>
						<position x="-0.298495" y="-1.500635" z="0.016778"/>
						<normal x="-0.195077" y="-0.980788" z="0.000000"/>
					</vertex>
					<vertex>
						<position x="-0.298493" y="-1.500636" z="38.000740"/>
						<normal x="-0.195077" y="-0.980788" z="0.000000"/>
					</vertex>
					<vertex>
						<position x="-0.585516" y="-1.413568" z="38.000740"/>
						<normal x="-0.382682" y="-0.923880" z="0.000000"/>
					</vertex>
					<vertex>
						<position x="-0.585519" y="-1.413567" z="0.016778"/>
						<normal x="-0.382682" y="-0.923880" z="0.000000"/>
					</vertex>
					<vertex>
						<position x="-0.585519" y="-1.413567" z="0.016778"/>
						<normal x="-0.382682" y="-0.923880" z="0.000000"/>
					</vertex>
					<vertex>
						<position x="-0.585516" y="-1.413568" z="38.000740"/>
						<normal x="-0.382682" y="-0.923880" z="0.000000"/>
					</vertex>
					<vertex>
						<position x="-0.850039" y="-1.272179" z="38.000740"/>
						<normal x="-0.555573" y="-0.831468" z="0.000000"/>
					</vertex>
					<vertex>
						<position x="-0.850042" y="-1.272177" z="0.016778"/>
						<normal x="-0.555573" y="-0.831468" z="0.000000"/>
					</vertex>
					<vertex>
						<position x="-0.850042" y="-1.272177" z="0.016778"/>
						<normal x="-0.555573" y="-0.831468" z="0.000000"/>
					</vertex>
					<vertex>
						<position x="-0.850039" y="-1.272179" z="38.000740"/>
						<normal x="-0.555573" y="-0.831468" z="0.000000"/>
					</vertex>
					<vertex>
						<position x="-1.081895" y="-1.081900" z="38.000740"/>
						<normal x="-0.707107" y="-0.707107" z="0.000000"/>
					</vertex>
					<vertex>
						<position x="-1.081898" y="-1.081897" z="0.016778"/>
						<normal x="-0.707107" y="-0.707107" z="0.000000"/>
					</vertex>
					<vertex>
						<position x="-1.081898" y="-1.081897" z="0.016778"/>
						<normal x="-0.707107" y="-0.707107" z="0.000000"/>
					</vertex>
					<vertex>
						<position x="-1.081895" y="-1.081900" z="38.000740"/>
						<normal x="-0.707107" y="-0.707107" z="0.000000"/>
					</vertex>
					<vertex>
						<position x="-1.272174" y="-0.850045" z="38.000740"/>
						<normal x="-0.831468" y="-0.555573" z="0.000000"/>
					</vertex>
					<vertex>
						<position x="-1.272178" y="-0.850041" z="0.016778"/>
						<normal x="-0.831468" y="-0.555573" z="0.000000"/>
					</vertex>
					<vertex>
						<position x="-1.272178" y="-0.850041" z="0.016778"/>
						<normal x="-0.831468" y="-0.555573" z="0.000000"/>
					</vertex>
					<vertex>
						<position x="-1.272174" y="-0.850045" z="38.000740"/>
						<normal x="-0.831468" y="-0.555573" z="0.000000"/>
					</vertex>
					<vertex>
						<position x="-1.413565" y="-0.585523" z="38.000740"/>
						<normal x="-0.923880" y="-0.382682" z="0.000000"/>
					</vertex>
					<vertex>
						<position x="-1.413568" y="-0.585518" z="0.016778"/>
						<normal x="-0.923880" y="-0.382682" z="0.000000"/>
					</vertex>
					<vertex>
						<position x="-1.413568" y="-0.585518" z="0.016778"/>
						<normal x="-0.923880" y="-0.382682" z="0.000000"/>
					</vertex>
					<vertex>
						<position x="-1.413565" y="-0.585523" z="38.000740"/>
						<normal x="-0.923880" y="-0.382682" z="0.000000"/>
					</vertex>
					<vertex>
						<position x="-1.500634" y="-0.298500" z="38.000740"/>
						<normal x="-0.980788" y="-0.195077" z="0.000000"/>
					</vertex>
					<vertex>
						<position x="-1.500635" y="-0.298493" z="0.016778"/>
						<normal x="-0.980788" y="-0.195077" z="0.000000"/>
					</vertex>
					<vertex>
						<position x="-1.500635" y="-0.298493" z="0.016778"/>
						<normal x="-0.980788" y="-0.195077" z="0.000000"/>
					</vertex>
					<vertex>
						<position x="-1.500634" y="-0.298500" z="38.000740"/>
						<normal x="-0.980788" y="-0.195077" z="0.000000"/>
					</vertex>
					<vertex>
						<position x="-1.530034" y="-0.000006" z="38.000740"/>
						<normal x="-1.000000" y="0.000000" z="0.000000"/>
					</vertex>
					<vertex>
						<position x="-1.530034" y="0.000002" z="0.016778"/>
						<normal x="-1.000000" y="0.000000" z="0.000000"/>
					</vertex>
					<vertex>
						<position x="-1.530034" y="0.000002" z="0.016778"/>
						<normal x="-1.000000" y="0.000000" z="0.000000"/>
					</vertex>
					<vertex>
						<position x="-1.530034" y="-0.000006" z="38.000740"/>
						<normal x="-1.000000" y="0.000000" z="0.000000"/>
					</vertex>
					<vertex>
						<position x="-1.500636" y="0.298488" z="38.000740"/>
						<normal x="-0.980788" y="0.195077" z="0.000000"/>
					</vertex>
					<vertex>
						<position x="-1.500635" y="0.298497" z="0.016778"/>
						<normal x="-0.980788" y="0.195077" z="0.000000"/>
					</vertex>
					<vertex>
						<position x="-1.500635" y="0.298497" z="0.016778"/>
						<normal x="-0.980788" y="0.195077" z="0.000000"/>
					</vertex>
					<vertex>
						<position x="-1.500636" y="0.298488" z="38.000740"/>
						<normal x="-0.980788" y="0.195077" z="0.000000"/>
					</vertex>
					<vertex>
						<position x="-1.413570" y="0.585512" z="38.000740"/>
						<normal x="-0.923880" y="0.382682" z="0.000000"/>
					</vertex>
					<vertex>
						<position x="-1.413567" y="0.585521" z="0.016778"/>
						<normal x="-0.923880" y="0.382682" z="0.000000"/>
					</vertex>
					<vertex>
						<position x="-1.413567" y="0.585521" z="0.016778"/>
						<normal x="-0.923880" y="0.382682" z="0.000000"/>
					</vertex>
					<vertex>
						<position x="-1.413570" y="0.585512" z="38.000740"/>
						<normal x="-0.923880" y="0.382682" z="0.000000"/>
					</vertex>
					<vertex>
						<position x="-1.272182" y="0.850035" z="38.000740"/>
						<normal x="-0.831468" y="0.555573" z="0.000000"/>
					</vertex>
					<vertex>
						<position x="-1.272176" y="0.850044" z="0.016778"/>
						<normal x="-0.831468" y="0.555573" z="0.000000"/>
					</vertex>
					<vertex>
						<position x="-1.272176" y="0.850044" z="0.016778"/>
						<normal x="-0.831468" y="0.555573" z="0.000000"/>
					</vertex>
					<vertex>
						<position x="-1.272182" y="0.850035" z="38.000740"/>
						<normal x="-0.831468" y="0.555573" z="0.000000"/>
					</vertex>
					<vertex>
						<position x="-1.081904" y="1.081892" z="38.000740"/>
						<normal x="-0.707107" y="0.707107" z="0.000000"/>
					</vertex>
					<vertex>
						<position x="-1.081896" y="1.081900" z="0.016778"/>
						<normal x="-0.707107" y="0.707107" z="0.000000"/>
					</vertex>
					<vertex>
						<position x="-1.081896" y="1.081900" z="0.016778"/>
						<normal x="-0.707107" y="0.707107" z="0.000000"/>
					</vertex>
					<vertex>
						<position x="-1.081904" y="1.081892" z="38.000740"/>
						<normal x="-0.707107" y="0.707107" z="0.000000"/>
					</vertex>
					<vertex>
						<position x="-0.850049" y="1.272172" z="38.000740"/>
						<normal x="-0.555573" y="0.831468" z="0.000000"/>
					</vertex>
					<vertex>
						<position x="-0.850040" y="1.272179" z="0.016778"/>
						<normal x="-0.555573" y="0.831468" z="0.000000"/>
					</vertex>
					<vertex>
						<position x="-0.850040" y="1.272179" z="0.016778"/>
						<normal x="-0.555573" y="0.831468" z="0.000000"/>
					</vertex>
					<vertex>
						<position x="-0.850049" y="1.272172" z="38.000740"/>
						<normal x="-0.555573" y="0.831468" z="0.000000"/>
					</vertex>
					<vertex>
						<position x="-0.585528" y="1.413564" z="38.000740"/>
						<normal x="-0.382682" y="0.923880" z="0.000000"/>
					</vertex>
					<vertex>
						<position x="-0.585517" y="1.413569" z="0.016778"/>
						<normal x="-0.382682" y="0.923880" z="0.000000"/>
					</vertex>
					<vertex>
						<position x="-0.585517" y="1.413569" z="0.016778"/>
						<normal x="-0.382682" y="0.923880" z="0.000000"/>
					</vertex>
					<vertex>
						<position x="-0.585528" y="1.413564" z="38.000740"/>
						<normal x="-0.382682" y="0.923880" z="0.000000"/>
					</vertex>
					<vertex>
						<position x="-0.298505" y="1.500634" z="38.000740"/>
						<normal x="-0.195077" y="0.980788" z="0.000000"/>
					</vertex>
					<vertex>
						<position x="-0.298492" y="1.500636" z="0.016778"/>
						<normal x="-0.195077" y="0.980788" z="0.000000"/>
					</vertex>
					<vertex>
						<position x="-0.298492" y="1.500636" z="0.016778"/>
						<normal x="-0.195077" y="0.980788" z="0.000000"/>
					</vertex>
					<vertex>
						<position x="-0.298505" y="1.500634" z="38.000740"/>
						<normal x="-0.195077" y="0.980788" z="0.000000"/>
					</vertex>
					<vertex>
						<position x="-0.000011" y="1.530035" z="38.000740"/>
						<normal x="0.000000" y="1.000000" z="0.000000"/>
					</vertex>
					<vertex>
						<position x="0.000003" y="1.530035" z="0.016778"/>
						<normal x="0.000000" y="1.000000" z="0.000000"/>
					</vertex>
					<vertex>
						<position x="0.000003" y="1.530035" z="0.016778"/>
						<normal x="0.000000" y="1.000000" z="0.000000"/>
					</vertex>
					<vertex>
						<position x="-0.000011" y="1.530035" z="38.000740"/>
						<normal x="0.000000" y="1.000000" z="0.000000"/>
					</vertex>
					<vertex>
						<position x="0.298484" y="1.500638" z="38.000740"/>
						<normal x="0.195077" y="0.980788" z="0.000000"/>
					</vertex>
					<vertex>
						<position x="0.298498" y="1.500635" z="0.016778"/>
						<normal x="0.195077" y="0.980788" z="0.000000"/>
					</vertex>
					<vertex>
						<position x="0.298498" y="1.500635" z="0.016778"/>
						<normal x="0.195077" y="0.980788" z="0.000000"/>
					</vertex>
					<vertex>
						<position x="0.298484" y="1.500638" z="38.000740"/>
						<normal x="0.195077" y="0.980788" z="0.000000"/>
					</vertex>
					<vertex>
						<position x="0.585508" y="1.413573" z="38.000740"/>
						<normal x="0.382682" y="0.923880" z="0.000000"/>
					</vertex>
					<vertex>
						<position x="0.585522" y="1.413567" z="0.016778"/>
						<normal x="0.382682" y="0.923880" z="0.000000"/>
					</vertex>
					<vertex>
						<position x="0.585522" y="1.413567" z="0.016778"/>
						<normal x="0.382682" y="0.923880" z="0.000000"/>
					</vertex>
					<vertex>
						<position x="0.585508" y="1.413573" z="38.000740"/>
						<normal x="0.382682" y="0.923880" z="0.000000"/>
					</vertex>
					<vertex>
						<position x="0.850031" y="1.272185" z="38.000740"/>
						<normal x="0.555573" y="0.831468" z="0.000000"/>
					</vertex>
					<vertex>
						<position x="0.850044" y="1.272176" z="0.016778"/>
						<normal x="0.555573" y="0.831468" z="0.000000"/>
					</vertex>
					<vertex>
						<position x="1.081900" y="1.081896" z="38.000740"/>
						<normal x="0.707107" y="0.707107" z="0.000000"/>
					</vertex>
					<vertex>
						<position x="1.081898" y="1.081898" z="0.016778"/>
						<normal x="0.707107" y="0.707107" z="0.000000"/>
					</vertex>
					<vertex>
						<position x="0.850044" y="1.272176" z="0.016778"/>
						<normal x="0.555573" y="0.831468" z="0.000000"/>
					</vertex>
					<vertex>
						<position x="0.850031" y="1.272185" z="38.000740"/>
						<normal x="0.555573" y="0.831468" z="0.000000"/>
					</vertex>
					<vertex>
						<position x="0.000000" y="0.000000" z="38.000740"/>
						<normal x="0.000000" y="0.000000" z="1.000000"/>
					</vertex>
					<vertex>
						<position x="1.081900" y="1.081896" z="38.000740"/>
						<normal x="0.000000" y="0.000000" z="1.000000"/>
					</vertex>
					<vertex>
						<position x="0.850031" y="1.272185" z="38.000740"/>
						<normal x="0.000000" y="0.000000" z="1.000000"/>
					</vertex>
					<vertex>
						<position x="0.850044" y="1.272176" z="0.016778"/>
						<normal x="0.000000" y="0.000000" z="-1.000000"/>
					</vertex>
					<vertex>
						<position x="1.081898" y="1.081898" z="0.016778"/>
						<normal x="0.000000" y="0.000000" z="-1.000000"/>
					</vertex>
					<vertex>
						<position x="0.000000" y="0.000000" z="0.016778"/>
						<normal x="0.000000" y="0.000000" z="-1.000000"/>
					</vertex>
					<vertex>
						<position x="0.000000" y="0.000000" z="38.000740"/>
						<normal x="0.000000" y="0.000000" z="1.000000"/>
					</vertex>
					<vertex>
						<position x="0.850031" y="1.272185" z="38.000740"/>
						<normal x="0.000000" y="0.000000" z="1.000000"/>
					</vertex>
					<vertex>
						<position x="0.585508" y="1.413573" z="38.000740"/>
						<normal x="0.000000" y="0.000000" z="1.000000"/>
					</vertex>
					<vertex>
						<position x="0.000000" y="0.000000" z="0.016778"/>
						<normal x="0.000000" y="0.000000" z="-1.000000"/>
					</vertex>
					<vertex>
						<position x="0.585522" y="1.413567" z="0.016778"/>
						<normal x="0.000000" y="0.000000" z="-1.000000"/>
					</vertex>
					<vertex>
						<position x="0.850044" y="1.272176" z="0.016778"/>
						<normal x="0.000000" y="0.000000" z="-1.000000"/>
					</vertex>
					<vertex>
						<position x="0.000000" y="0.000000" z="38.000740"/>
						<normal x="0.000000" y="0.000000" z="1.000000"/>
					</vertex>
					<vertex>
						<position x="0.585508" y="1.413573" z="38.000740"/>
						<normal x="0.000000" y="0.000000" z="1.000000"/>
					</vertex>
					<vertex>
						<position x="0.298484" y="1.500638" z="38.000740"/>
						<normal x="0.000000" y="0.000000" z="1.000000"/>
					</vertex>
					<vertex>
						<position x="0.000000" y="0.000000" z="0.016778"/>
						<normal x="0.000000" y="0.000000" z="-1.000000"/>
					</vertex>
					<vertex>
						<position x="0.298498" y="1.500635" z="0.016778"/>
						<normal x="0.000000" y="0.000000" z="-1.000000"/>
					</vertex>
					<vertex>
						<position x="0.585522" y="1.413567" z="0.016778"/>
						<normal x="0.000000" y="0.000000" z="-1.000000"/>
					</vertex>
					<vertex>
						<position x="0.000000" y="0.000000" z="38.000740"/>
						<normal x="0.000000" y="0.000000" z="1.000000"/>
					</vertex>
					<vertex>
						<position x="0.298484" y="1.500638" z="38.000740"/>
						<normal x="0.000000" y="0.000000" z="1.000000"/>
					</vertex>
					<vertex>
						<position x="-0.000011" y="1.530035" z="38.000740"/>
						<normal x="0.000000" y="0.000000" z="1.000000"/>
					</vertex>
					<vertex>
						<position x="0.000000" y="0.000000" z="0.016778"/>
						<normal x="0.000000" y="0.000000" z="-1.000000"/>
					</vertex>
					<vertex>
						<position x="0.000003" y="1.530035" z="0.016778"/>
						<normal x="0.000000" y="0.000000" z="-1.000000"/>
					</vertex>
					<vertex>
						<position x="0.298498" y="1.500635" z="0.016778"/>
						<normal x="0.000000" y="0.000000" z="-1.000000"/>
					</vertex>
					<vertex>
						<position x="0.000000" y="0.000000" z="38.000740"/>
						<normal x="0.000000" y="0.000000" z="1.000000"/>
					</vertex>
					<vertex>
						<position x="-0.000011" y="1.530035" z="38.000740"/>
						<normal x="0.000000" y="0.000000" z="1.000000"/>
					</vertex>
					<vertex>
						<position x="-0.298505" y="1.500634" z="38.000740"/>
						<normal x="0.000000" y="0.000000" z="1.000000"/>
					</vertex>
					<vertex>
						<position x="0.000000" y="0.000000" z="0.016778"/>
						<normal x="0.000000" y="0.000000" z="-1.000000"/>
					</vertex>
					<vertex>
						<position x="-0.298492" y="1.500636" z="0.016778"/>
						<normal x="0.000000" y="0.000000" z="-1.000000"/>
					</vertex>
					<vertex>
						<position x="0.000003" y="1.530035" z="0.016778"/>
						<normal x="0.000000" y="0.000000" z="-1.000000"/>
					</vertex>
					<vertex>
						<position x="0.000000" y="0.000000" z="38.000740"/>
						<normal x="0.000000" y="0.000000" z="1.000000"/>
					</vertex>
					<vertex>
						<position x="-0.298505" y="1.500634" z="38.000740"/>
						<normal x="0.000000" y="0.000000" z="1.000000"/>
					</vertex>
					<vertex>
						<position x="-0.585528" y="1.413564" z="38.000740"/>
						<normal x="0.000000" y="0.000000" z="1.000000"/>
					</vertex>
					<vertex>
						<position x="0.000000" y="0.000000" z="0.016778"/>
						<normal x="0.000000" y="0.000000" z="-1.000000"/>
					</vertex>
					<vertex>
						<position x="-0.585517" y="1.413569" z="0.016778"/>
						<normal x="0.000000" y="0.000000" z="-1.000000"/>
					</vertex>
					<vertex>
						<position x="-0.298492" y="1.500636" z="0.016778"/>
						<normal x="0.000000" y="0.000000" z="-1.000000"/>
					</vertex>
					<vertex>
						<position x="0.000000" y="0.000000" z="38.000740"/>
						<normal x="0.000000" y="0.000000" z="1.000000"/>
					</vertex>
					<vertex>
						<position x="-0.585528" y="1.413564" z="38.000740"/>
						<normal x="0.000000" y="0.000000" z="1.000000"/>
					</vertex>
					<vertex>
						<position x="-0.850049" y="1.272172" z="38.000740"/>
						<normal x="0.000000" y="0.000000" z="1.000000"/>
					</vertex>
					<vertex>
						<position x="0.000000" y="0.000000" z="0.016778"/>
						<normal x="0.000000" y="0.000000" z="-1.000000"/>
					</vertex>
					<vertex>
						<position x="-0.850040" y="1.272179" z="0.016778"/>
						<normal x="0.000000" y="0.000000" z="-1.000000"/>
					</vertex>
					<vertex>
						<position x="-0.585517" y="1.413569" z="0.016778"/>
						<normal x="0.000000" y="0.000000" z="-1.000000"/>
					</vertex>
					<vertex>
						<position x="0.000000" y="0.000000" z="38.000740"/>
						<normal x="0.000000" y="0.000000" z="1.000000"/>
					</vertex>
					<vertex>
						<position x="-0.850049" y="1.272172" z="38.000740"/>
						<normal x="0.000000" y="0.000000" z="1.000000"/>
					</vertex>
					<vertex>
						<position x="-1.081904" y="1.081892" z="38.000740"/>
						<normal x="0.000000" y="0.000000" z="1.000000"/>
					</vertex>
					<vertex>
						<position x="0.000000" y="0.000000" z="0.016778"/>
						<normal x="0.000000" y="0.000000" z="-1.000000"/>
					</vertex>
					<vertex>
						<position x="-1.081896" y="1.081900" z="0.016778"/>
						<normal x="0.000000" y="0.000000" z="-1.000000"/>
					</vertex>
					<vertex>
						<position x="-0.850040" y="1.272179" z="0.016778"/>
						<normal x="0.000000" y="0.000000" z="-1.000000"/>
					</vertex>
					<vertex>
						<position x="0.000000" y="0.000000" z="38.000740"/>
						<normal x="0.000000" y="0.000000" z="1.000000"/>
					</vertex>
					<vertex>
						<position x="-1.081904" y="1.081892" z="38.000740"/>
						<normal x="0.000000" y="0.000000" z="1.000000"/>
					</vertex>
					<vertex>
						<position x="-1.272182" y="0.850035" z="38.000740"/>
						<normal x="0.000000" y="0.000000" z="1.000000"/>
					</vertex>
					<vertex>
						<position x="0.000000" y="0.000000" z="0.016778"/>
						<normal x="0.000000" y="0.000000" z="-1.000000"/>
					</vertex>
					<vertex>
						<position x="-1.272176" y="0.850044" z="0.016778"/>
						<normal x="0.000000" y="0.000000" z="-1.000000"/>
					</vertex>
					<vertex>
						<position x="-1.081896" y="1.081900" z="0.016778"/>
						<normal x="0.000000" y="0.000000" z="-1.000000"/>
					</vertex>
					<vertex>
						<position x="0.000000" y="0.000000" z="38.000740"/>
						<normal x="0.000000" y="0.000000" z="1.000000"/>
					</vertex>
					<vertex>
						<position x="-1.272182" y="0.850035" z="38.000740"/>
						<normal x="0.000000" y="0.000000" z="1.000000"/>
					</vertex>
					<vertex>
						<position x="-1.413570" y="0.585512" z="38.000740"/>
						<normal x="0.000000" y="0.000000" z="1.000000"/>
					</vertex>
					<vertex>
						<position x="0.000000" y="0.000000" z="0.016778"/>
						<normal x="0.000000" y="0.000000" z="-1.000000"/>
					</vertex>
					<vertex>
						<position x="-1.413567" y="0.585521" z="0.016778"/>
						<normal x="0.000000" y="0.000000" z="-1.000000"/>
					</vertex>
					<vertex>
						<position x="-1.272176" y="0.850044" z="0.016778"/>
						<normal x="0.000000" y="0.000000" z="-1.000000"/>
					</vertex>
					<vertex>
						<position x="0.000000" y="0.000000" z="38.000740"/>
						<normal x="0.000000" y="0.000000" z="1.000000"/>
					</vertex>
					<vertex>
						<position x="-1.413570" y="0.585512" z="38.000740"/>
						<normal x="0.000000" y="0.000000" z="1.000000"/>
					</vertex>
					<vertex>
						<position x="-1.500636" y="0.298488" z="38.000740"/>
						<normal x="0.000000" y="0.000000" z="1.000000"/>
					</vertex>
					<vertex>
						<position x="0.000000" y="0.000000" z="0.016778"/>
						<normal x="0.000000" y="0.000000" z="-1.000000"/>
					</vertex>
					<vertex>
						<position x="-1.500635" y="0.298497" z="0.016778"/>
						<normal x="0.000000" y="0.000000" z="-1.000000"/>
					</vertex>
					<vertex>
						<position x="-1.413567" y="0.585521" z="0.016778"/>
						<normal x="0.000000" y="0.000000" z="-1.000000"/>
					</vertex>
					<vertex>
						<position x="0.000000" y="0.000000" z="38.000740"/>
						<normal x="0.000000" y="0.000000" z="1.000000"/>
					</vertex>
					<vertex>
						<position x="-1.500636" y="0.298488" z="38.000740"/>
						<normal x="0.000000" y="0.000000" z="1.000000"/>
					</vertex>
					<vertex>
						<position x="-1.530034" y="-0.000006" z="38.000740"/>
						<normal x="0.000000" y="0.000000" z="1.000000"/>
					</vertex>
					<vertex>
						<position x="0.000000" y="0.000000" z="0.016778"/>
						<normal x="0.000000" y="0.000000" z="-1.000000"/>
					</vertex>
					<vertex>
						<position x="-1.530034" y="0.000002" z="0.016778"/>
						<normal x="0.000000" y="0.000000" z="-1.000000"/>
					</vertex>
					<vertex>
						<position x="-1.500635" y="0.298497" z="0.016778"/>
						<normal x="0.000000" y="0.000000" z="-1.000000"/>
					</vertex>
					<vertex>
						<position x="0.000000" y="0.000000" z="38.000740"/>
						<normal x="0.000000" y="0.000000" z="1.000000"/>
					</vertex>
					<vertex>
						<position x="-1.530034" y="-0.000006" z="38.000740"/>
						<normal x="0.000000" y="0.000000" z="1.000000"/>
					</vertex>
					<vertex>
						<position x="-1.500634" y="-0.298500" z="38.000740"/>
						<normal x="0.000000" y="0.000000" z="1.000000"/>
					</vertex>
					<vertex>
						<position x="0.000000" y="0.000000" z="0.016778"/>
						<normal x="0.000000" y="0.000000" z="-1.000000"/>
					</vertex>
					<vertex>
						<position x="-1.500635" y="-0.298493" z="0.016778"/>
						<normal x="0.000000" y="0.000000" z="-1.000000"/>
					</vertex>
					<vertex>
						<position x="-1.530034" y="0.000002" z="0.016778"/>
						<normal x="0.000000" y="0.000000" z="-1.000000"/>
					</vertex>
					<vertex>
						<position x="0.000000" y="0.000000" z="38.000740"/>
						<normal x="0.000000" y="0.000000" z="1.000000"/>
					</vertex>
					<vertex>
						<position x="-1.500634" y="-0.298500" z="38.000740"/>
						<normal x="0.000000" y="0.000000" z="1.000000"/>
					</vertex>
					<vertex>
						<position x="-1.413565" y="-0.585523" z="38.000740"/>
						<normal x="0.000000" y="0.000000" z="1.000000"/>
					</vertex>
					<vertex>
						<position x="0.000000" y="0.000000" z="0.016778"/>
						<normal x="0.000000" y="0.000000" z="-1.000000"/>
					</vertex>
					<vertex>
						<position x="-1.413568" y="-0.585518" z="0.016778"/>
						<normal x="0.000000" y="0.000000" z="-1.000000"/>
					</vertex>
					<vertex>
						<position x="-1.500635" y="-0.298493" z="0.016778"/>
						<normal x="0.000000" y="0.000000" z="-1.000000"/>
					</vertex>
					<vertex>
						<position x="0.000000" y="0.000000" z="38.000740"/>
						<normal x="0.000000" y="0.000000" z="1.000000"/>
					</vertex>
					<vertex>
						<position x="-1.413565" y="-0.585523" z="38.000740"/>
						<normal x="0.000000" y="0.000000" z="1.000000"/>
					</vertex>
					<vertex>
						<position x="-1.272174" y="-0.850045" z="38.000740"/>
						<normal x="0.000000" y="0.000000" z="1.000000"/>
					</vertex>
					<vertex>
						<position x="0.000000" y="0.000000" z="0.016778"/>
						<normal x="0.000000" y="0.000000" z="-1.000000"/>
					</vertex>
					<vertex>
						<position x="-1.272178" y="-0.850041" z="0.016778"/>
						<normal x="0.000000" y="0.000000" z="-1.000000"/>
					</vertex>
					<vertex>
						<position x="-1.413568" y="-0.585518" z="0.016778"/>
						<normal x="0.000000" y="0.000000" z="-1.000000"/>
					</vertex>
					<vertex>
						<position x="0.000000" y="0.000000" z="38.000740"/>
						<normal x="0.000000" y="0.000000" z="1.000000"/>
					</vertex>
					<vertex>
						<position x="-1.272174" y="-0.850045" z="38.000740"/>
						<normal x="0.000000" y="0.000000" z="1.000000"/>
					</vertex>
					<vertex>
						<position x="-1.081895" y="-1.081900" z="38.000740"/>
						<normal x="0.000000" y="0.000000" z="1.000000"/>
					</vertex>
					<vertex>
						<position x="0.000000" y="0.000000" z="0.016778"/>
						<normal x="0.000000" y="0.000000" z="-1.000000"/>
					</vertex>
					<vertex>
						<position x="-1.081898" y="-1.081897" z="0.016778"/>
						<normal x="0.000000" y="0.000000" z="-1.000000"/>
					</vertex>
					<vertex>
						<position x="-1.272178" y="-0.850041" z="0.016778"/>
						<normal x="0.000000" y="0.000000" z="-1.000000"/>
					</vertex>
					<vertex>
						<position x="0.000000" y="0.000000" z="38.000740"/>
						<normal x="0.000000" y="0.000000" z="1.000000"/>
					</vertex>
					<vertex>
						<position x="-1.081895" y="-1.081900" z="38.000740"/>
						<normal x="0.000000" y="0.000000" z="1.000000"/>
					</vertex>
					<vertex>
						<position x="-0.850039" y="-1.272179" z="38.000740"/>
						<normal x="0.000000" y="0.000000" z="1.000000"/>
					</vertex>
					<vertex>
						<position x="0.000000" y="0.000000" z="0.016778"/>
						<normal x="0.000000" y="0.000000" z="-1.000000"/>
					</vertex>
					<vertex>
						<position x="-0.850042" y="-1.272177" z="0.016778"/>
						<normal x="0.000000" y="0.000000" z="-1.000000"/>
					</vertex>
					<vertex>
						<position x="-1.081898" y="-1.081897" z="0.016778"/>
						<normal x="0.000000" y="0.000000" z="-1.000000"/>
					</vertex>
					<vertex>
						<position x="0.000000" y="0.000000" z="38.000740"/>
						<normal x="0.000000" y="0.000000" z="1.000000"/>
					</vertex>
					<vertex>
						<position x="-0.850039" y="-1.272179" z="38.000740"/>
						<normal x="0.000000" y="0.000000" z="1.000000"/>
					</vertex>
					<vertex>
						<position x="-0.585516" y="-1.413568" z="38.000740"/>
						<normal x="0.000000" y="0.000000" z="1.000000"/>
					</vertex>
					<vertex>
						<position x="0.000000" y="0.000000" z="0.016778"/>
						<normal x="0.000000" y="0.000000" z="-1.000000"/>
					</vertex>
					<vertex>
						<position x="-0.585519" y="-1.413567" z="0.016778"/>
						<normal x="0.000000" y="0.000000" z="-1.000000"/>
					</vertex>
					<vertex>
						<position x="-0.850042" y="-1.272177" z="0.016778"/>
						<normal x="0.000000" y="0.000000" z="-1.000000"/>
					</vertex>
					<vertex>
						<position x="0.000000" y="0.000000" z="38.000740"/>
						<normal x="0.000000" y="0.000000" z="1.000000"/>
					</vertex>
					<vertex>
						<position x="-0.585516" y="-1.413568" z="38.000740"/>
						<normal x="0.000000" y="0.000000" z="1.000000"/>
					</vertex>
					<vertex>
						<position x="-0.298493" y="-1.500636" z="38.000740"/>
						<normal x="0.000000" y="0.000000" z="1.000000"/>
					</vertex>
					<vertex>
						<position x="0.000000" y="0.000000" z="0.016778"/>
						<normal x="0.000000" y="0.000000" z="-1.000000"/>
					</vertex>
					<vertex>
						<position x="-0.298495" y="-1.500635" z="0.016778"/>
						<normal x="0.000000" y="0.000000" z="-1.000000"/>
					</vertex>
					<vertex>
						<position x="-0.585519" y="-1.413567" z="0.016778"/>
						<normal x="0.000000" y="0.000000" z="-1.000000"/>
					</vertex>
					<vertex>
						<position x="0.000000" y="0.000000" z="38.000740"/>
						<normal x="0.000000" y="0.000000" z="1.000000"/>
					</vertex>
					<vertex>
						<position x="-0.298493" y="-1.500636" z="38.000740"/>
						<normal x="0.000000" y="0.000000" z="1.000000"/>
					</vertex>
					<vertex>
						<position x="0.000002" y="-1.530034" z="38.000740"/>
						<normal x="0.000000" y="0.000000" z="1.000000"/>
					</vertex>
					<vertex>
						<position x="0.000000" y="0.000000" z="0.016778"/>
						<normal x="0.000000" y="0.000000" z="-1.000000"/>
					</vertex>
					<vertex>
						<position x="-0.000000" y="-1.530034" z="0.016778"/>
						<normal x="0.000000" y="0.000000" z="-1.000000"/>
					</vertex>
					<vertex>
						<position x="-0.298495" y="-1.500635" z="0.016778"/>
						<normal x="0.000000" y="0.000000" z="-1.000000"/>
					</vertex>
					<vertex>
						<position x="0.000000" y="0.000000" z="38.000740"/>
						<normal x="0.000000" y="0.000000" z="1.000000"/>
					</vertex>
					<vertex>
						<position x="0.000002" y="-1.530034" z="38.000740"/>
						<normal x="0.000000" y="0.000000" z="1.000000"/>
					</vertex>
					<vertex>
						<position x="0.298496" y="-1.500635" z="38.000740"/>
						<normal x="0.000000" y="0.000000" z="1.000000"/>
					</vertex>
					<vertex>
						<position x="0.000000" y="0.000000" z="0.016778"/>
						<normal x="0.000000" y="0.000000" z="-1.000000"/>
					</vertex>
					<vertex>
						<position x="0.298495" y="-1.500635" z="0.016778"/>
						<normal x="0.000000" y="0.000000" z="-1.000000"/>
					</vertex>
					<vertex>
						<position x="-0.000000" y="-1.530034" z="0.016778"/>
						<normal x="0.000000" y="0.000000" z="-1.000000"/>
					</vertex>
					<vertex>
						<position x="0.000000" y="0.000000" z="38.000740"/>
						<normal x="0.000000" y="0.000000" z="1.000000"/>
					</vertex>
					<vertex>
						<position x="0.298496" y="-1.500635" z="38.000740"/>
						<normal x="0.000000" y="0.000000" z="1.000000"/>
					</vertex>
					<vertex>
						<position x="0.585519" y="-1.413568" z="38.000740"/>
						<normal x="0.000000" y="0.000000" z="1.000000"/>
					</vertex>
					<vertex>
						<position x="0.000000" y="0.000000" z="0.016778"/>
						<normal x="0.000000" y="0.000000" z="-1.000000"/>
					</vertex>
					<vertex>
						<position x="0.585519" y="-1.413568" z="0.016778"/>
						<normal x="0.000000" y="0.000000" z="-1.000000"/>
					</vertex>
					<vertex>
						<position x="0.298495" y="-1.500635" z="0.016778"/>
						<normal x="0.000000" y="0.000000" z="-1.000000"/>
					</vertex>
					<vertex>
						<position x="0.000000" y="0.000000" z="38.000740"/>
						<normal x="0.000000" y="0.000000" z="1.000000"/>
					</vertex>
					<vertex>
						<position x="0.585519" y="-1.413568" z="38.000740"/>
						<normal x="0.000000" y="0.000000" z="1.000000"/>
					</vertex>
					<vertex>
						<position x="0.850042" y="-1.272177" z="38.000740"/>
						<normal x="0.000000" y="0.000000" z="1.000000"/>
					</vertex>
					<vertex>
						<position x="0.000000" y="0.000000" z="0.016778"/>
						<normal x="0.000000" y="0.000000" z="-1.000000"/>
					</vertex>
					<vertex>
						<position x="0.850042" y="-1.272177" z="0.016778"/>
						<normal x="0.000000" y="0.000000" z="-1.000000"/>
					</vertex>
					<vertex>
						<position x="0.585519" y="-1.413568" z="0.016778"/>
						<normal x="0.000000" y="0.000000" z="-1.000000"/>
					</vertex>
					<vertex>
						<position x="0.000000" y="0.000000" z="38.000740"/>
						<normal x="0.000000" y="0.000000" z="1.000000"/>
					</vertex>
					<vertex>
						<position x="0.850042" y="-1.272177" z="38.000740"/>
						<normal x="0.000000" y="0.000000" z="1.000000"/>
					</vertex>
					<vertex>
						<position x="1.081897" y="-1.081898" z="38.000740"/>
						<normal x="0.000000" y="0.000000" z="1.000000"/>
					</vertex>
					<vertex>
						<position x="0.000000" y="0.000000" z="0.016778"/>
						<normal x="0.000000" y="0.000000" z="-1.000000"/>
					</vertex>
					<vertex>
						<position x="1.081898" y="-1.081898" z="0.016778"/>
						<normal x="0.000000" y="0.000000" z="-1.000000"/>
					</vertex>
					<vertex>
						<position x="0.850042" y="-1.272177" z="0.016778"/>
						<normal x="0.000000" y="0.000000" z="-1.000000"/>
					</vertex>
					<vertex>
						<position x="0.000000" y="0.000000" z="38.000740"/>
						<normal x="0.000000" y="0.000000" z="1.000000"/>
					</vertex>
					<vertex>
						<position x="1.081897" y="-1.081898" z="38.000740"/>
						<normal x="0.000000" y="0.000000" z="1.000000"/>
					</vertex>
					<vertex>
						<position x="1.272177" y="-0.850043" z="38.000740"/>
						<normal x="0.000000" y="0.000000" z="1.000000"/>
					</vertex>
					<vertex>
						<position x="0.000000" y="0.000000" z="0.016778"/>
						<normal x="0.000000" y="0.000000" z="-1.000000"/>
					</vertex>
					<vertex>
						<position x="1.272178" y="-0.850041" z="0.016778"/>
						<normal x="0.000000" y="0.000000" z="-1.000000"/>
					</vertex>
					<vertex>
						<position x="1.081898" y="-1.081898" z="0.016778"/>
						<normal x="0.000000" y="0.000000" z="-1.000000"/>
					</vertex>
					<vertex>
						<position x="0.000000" y="0.000000" z="38.000740"/>
						<normal x="0.000000" y="0.000000" z="1.000000"/>
					</vertex>
					<vertex>
						<position x="1.272177" y="-0.850043" z="38.000740"/>
						<normal x="0.000000" y="0.000000" z="1.000000"/>
					</vertex>
					<vertex>
						<position x="1.413567" y="-0.585521" z="38.000740"/>
						<normal x="0.000000" y="0.000000" z="1.000000"/>
					</vertex>
					<vertex>
						<position x="0.000000" y="0.000000" z="0.016778"/>
						<normal x="0.000000" y="0.000000" z="-1.000000"/>
					</vertex>
					<vertex>
						<position x="1.413568" y="-0.585518" z="0.016778"/>
						<normal x="0.000000" y="0.000000" z="-1.000000"/>
					</vertex>
					<vertex>
						<position x="1.272178" y="-0.850041" z="0.016778"/>
						<normal x="0.000000" y="0.000000" z="-1.000000"/>
					</vertex>
					<vertex>
						<position x="0.000000" y="0.000000" z="38.000740"/>
						<normal x="0.000000" y="0.000000" z="1.000000"/>
					</vertex>
					<vertex>
						<position x="1.413567" y="-0.585521" z="38.000740"/>
						<normal x="0.000000" y="0.000000" z="1.000000"/>
					</vertex>
					<vertex>
						<position x="1.500635" y="-0.298497" z="38.000740"/>
						<normal x="0.000000" y="0.000000" z="1.000000"/>
					</vertex>
					<vertex>
						<position x="0.000000" y="0.000000" z="0.016778"/>
						<normal x="0.000000" y="0.000000" z="-1.000000"/>
					</vertex>
					<vertex>
						<position x="1.500636" y="-0.298494" z="0.016778"/>
						<normal x="0.000000" y="0.000000" z="-1.000000"/>
					</vertex>
					<vertex>
						<position x="1.413568" y="-0.585518" z="0.016778"/>
						<normal x="0.000000" y="0.000000" z="-1.000000"/>
					</vertex>
					<vertex>
						<position x="0.000000" y="0.000000" z="38.000740"/>
						<normal x="0.000000" y="0.000000" z="1.000000"/>
					</vertex>
					<vertex>
						<position x="1.500635" y="-0.298497" z="38.000740"/>
						<normal x="0.000000" y="0.000000" z="1.000000"/>
					</vertex>
					<vertex>
						<position x="1.530035" y="-0.000003" z="38.000740"/>
						<normal x="0.000000" y="0.000000" z="1.000000"/>
					</vertex>
					<vertex>
						<position x="0.000000" y="0.000000" z="0.016778"/>
						<normal x="0.000000" y="0.000000" z="-1.000000"/>
					</vertex>
					<vertex>
						<position x="1.530035" y="0.000000" z="0.016778"/>
						<normal x="0.000000" y="0.000000" z="-1.000000"/>
					</vertex>
					<vertex>
						<position x="1.500636" y="-0.298494" z="0.016778"/>
						<normal x="0.000000" y="0.000000" z="-1.000000"/>
					</vertex>
					<vertex>
						<position x="0.000000" y="0.000000" z="38.000740"/>
						<normal x="0.000000" y="0.000000" z="1.000000"/>
					</vertex>
					<vertex>
						<position x="1.530035" y="-0.000003" z="38.000740"/>
						<normal x="0.000000" y="0.000000" z="1.000000"/>
					</vertex>
					<vertex>
						<position x="1.500637" y="0.298492" z="38.000740"/>
						<normal x="0.000000" y="0.000000" z="1.000000"/>
					</vertex>
					<vertex>
						<position x="0.000000" y="0.000000" z="0.016778"/>
						<normal x="0.000000" y="0.000000" z="-1.000000"/>
					</vertex>
					<vertex>
						<position x="1.500636" y="0.298495" z="0.016778"/>
						<normal x="0.000000" y="0.000000" z="-1.000000"/>
					</vertex>
					<vertex>
						<position x="1.530035" y="0.000000" z="0.016778"/>
						<normal x="0.000000" y="0.000000" z="-1.000000"/>
					</vertex>
					<vertex>
						<position x="0.000000" y="0.000000" z="38.000740"/>
						<normal x="0.000000" y="0.000000" z="1.000000"/>
					</vertex>
					<vertex>
						<position x="1.500637" y="0.298492" z="38.000740"/>
						<normal x="0.000000" y="0.000000" z="1.000000"/>
					</vertex>
					<vertex>
						<position x="1.413569" y="0.585516" z="38.000740"/>
						<normal x="0.000000" y="0.000000" z="1.000000"/>
					</vertex>
					<vertex>
						<position x="0.000000" y="0.000000" z="0.016778"/>
						<normal x="0.000000" y="0.000000" z="-1.000000"/>
					</vertex>
					<vertex>
						<position x="1.413568" y="0.585519" z="0.016778"/>
						<normal x="0.000000" y="0.000000" z="-1.000000"/>
					</vertex>
					<vertex>
						<position x="1.500636" y="0.298495" z="0.016778"/>
						<normal x="0.000000" y="0.000000" z="-1.000000"/>
					</vertex>
					<vertex>
						<position x="0.000000" y="0.000000" z="38.000740"/>
						<normal x="0.000000" y="0.000000" z="1.000000"/>
					</vertex>
					<vertex>
						<position x="1.413569" y="0.585516" z="38.000740"/>
						<normal x="0.000000" y="0.000000" z="1.000000"/>
					</vertex>
					<vertex>
						<position x="1.272179" y="0.850039" z="38.000740"/>
						<normal x="0.000000" y="0.000000" z="1.000000"/>
					</vertex>
					<vertex>
						<position x="0.000000" y="0.000000" z="0.016778"/>
						<normal x="0.000000" y="0.000000" z="-1.000000"/>
					</vertex>
					<vertex>
						<position x="1.272178" y="0.850042" z="0.016778"/>
						<normal x="0.000000" y="0.000000" z="-1.000000"/>
					</vertex>
					<vertex>
						<position x="1.413568" y="0.585519" z="0.016778"/>
						<normal x="0.000000" y="0.000000" z="-1.000000"/>
					</vertex>
					<vertex>
						<position x="0.000000" y="0.000000" z="38.000740"/>
						<normal x="0.000000" y="0.000000" z="1.000000"/>
					</vertex>
					<vertex>
						<position x="1.272179" y="0.850039" z="38.000740"/>
						<normal x="0.000000" y="0.000000" z="1.000000"/>
					</vertex>
					<vertex>
						<position x="1.081900" y="1.081896" z="38.000740"/>
						<normal x="0.000000" y="0.000000" z="1.000000"/>
					</vertex>
					<vertex>
						<position x="0.000000" y="0.000000" z="0.016778"/>
						<normal x="0.000000" y="0.000000" z="-1.000000"/>
					</vertex>
					<vertex>
						<position x="1.081898" y="1.081898" z="0.016778"/>
						<normal x="0.000000" y="0.000000" z="-1.000000"/>
					</vertex>
					<vertex>
						<position x="1.272178" y="0.850042" z="0.016778"/>
						<normal x="0.000000" y="0.000000" z="-1.000000"/>
					</vertex>
				</vertexbuffer>
			</geometry>
		</submesh>
	</submeshes>
</mesh>
